tfkit/__init__.py
tfkit/__main__.py
tfkit/cli.py
tfkit/analyzer/__init__.py
tfkit/analyzer/models.py
tfkit/analyzer/project.py
tfkit/analyzer/terraform_analyzer.py
tfkit/commands/__init__.py
tfkit/commands/examples.py
tfkit/commands/export.py
tfkit/commands/scan.py
tfkit/commands/utils.py
tfkit/commands/validate.py
tfkit/templates/__init__.py
tfkit/templates/classic-template.html.j2
tfkit/templates/dashboard-template.html.j2
tfkit/templates/graph-template.html.j2
tfkit/templates/template_factory.py
tfkit/templates/theme_manager.py
tfkit/validator/__init__.py
tfkit/validator/models.py
tfkit/validator/validator.py
tfkit/visualizer/__init__.py
tfkit/visualizer/generator.py
tfkit/visualizer/graph_builder.py
tfkit_py-0.4.57.dist-info/METADATA
tfkit_py-0.4.57.dist-info/WHEEL
tfkit_py-0.4.57.dist-info/entry_points.txt
tfkit_py-0.4.57.dist-info/licenses/LICENSE
tfkit_py-0.4.57.dist-info/RECORD
