Metadata-Version: 2.4
Name: tfkit-py
Version: 0.4.57
Summary: Advanced Terraform Intelligence & Analysis Suite
Project-URL: Homepage, https://tfkit.netlify.app
Project-URL: Documentation, https://tfkit.netlify.app/docs
Project-URL: Repository, https://github.com/ivasik-k7/tfkit
Project-URL: Issues, https://github.com/ivasik-k7/tfkit/issues
Author-email: Ivan Kovtun <kovtun.ivan@proton.me>
Maintainer-email: Ivan Kovtun <kovtun.ivan@proton.me>
License: MIT
License-File: LICENSE
Keywords: analysis,cli,cost-optimization,devops,iac,infrastructure-as-code,security,terraform,visualization
Classifier: Development Status :: 4 - Beta
Classifier: Environment :: Console
Classifier: Intended Audience :: Developers
Classifier: Intended Audience :: System Administrators
Classifier: License :: OSI Approved :: MIT License
Classifier: Operating System :: OS Independent
Classifier: Programming Language :: Python :: 3
Classifier: Programming Language :: Python :: 3.8
Classifier: Programming Language :: Python :: 3.9
Classifier: Programming Language :: Python :: 3.10
Classifier: Programming Language :: Python :: 3.11
Classifier: Programming Language :: Python :: 3.12
Classifier: Topic :: Software Development :: Libraries :: Python Modules
Classifier: Topic :: System :: Systems Administration
Classifier: Topic :: Utilities
Requires-Python: >=3.8
Requires-Dist: click>=8.1.0
Requires-Dist: jinja2>=3.1.0
Requires-Dist: python-hcl2>=4.3.0
Requires-Dist: pyyaml>=6.0.0
Requires-Dist: rich>=13.0.0
Requires-Dist: toml>=0.10.2
Provides-Extra: dev
Requires-Dist: black>=23.0.0; extra == 'dev'
Requires-Dist: build>=1.0.0; extra == 'dev'
Requires-Dist: isort>=5.12.0; extra == 'dev'
Requires-Dist: mypy>=1.0.0; extra == 'dev'
Requires-Dist: pytest-cov>=4.0.0; extra == 'dev'
Requires-Dist: pytest>=7.0.0; extra == 'dev'
Requires-Dist: ruff>=0.1.0; extra == 'dev'
Requires-Dist: twine>=4.0.0; extra == 'dev'
